<?xml version="1.0" encoding="UTF-8"?>

<lexeme id="leac-noun" xmlns:xsi="http://www.w3.org/2001/XMLSchema-instance" xsi:noNamespaceSchemaLocation="../lexeme.xsd">
    <form>
      <orth>leac</orth>
    </form>
    <form>
      <orth>lice</orth>
    </form>
    <form>
      <orth>leacan</orth>
    </form>
    <trans>slab</trans>
    <trans>flagstone</trans>
    <trans>flat stone</trans>
    <trans>tombstone</trans>
    <trans>tile</trans>
    <note>Listed in An Seotal: Maths, as 'tile'.</note>
  </lexeme>
