<?xml version="1.0" encoding="UTF-8"?>

<ainmear_boireann id="seabhag" xmlns:xsi="http://www.w3.org/2001/XMLSchema-instance" xsi:noNamespaceSchemaLocation="../lexeme.xsd">
  <form>
    <orth>seabhag</orth>
  </form>
  <form>
    <orth>seabhaig</orth>
  </form>
  <form>
    <orth>seabhaige</orth>
  </form>
  <form>
    <orth>seabhagan</orth>
  </form>
  <trans>hawk</trans>
  <trans>Accipitriformes spp.</trans>
  <note>From Scottish Natural Heritage's Faclan Nàdair.</note>
  <note>Audio: http://www.snh.org.uk/gaidhlig/audio/seabhag.mp3</note>
  <note>Listed in An Seotal: Science.</note>
  <note>Listed in CM as 'hawk, falcon'.</note>
</ainmear_boireann>
